[{"date": "2024-08-01", "open": 0.93, "close": 0.933, "high": 0.938, "low": 0.927, "volume": 848823.0, "amount": 0.0}, {"date": "2024-08-02", "open": 0.926, "close": 0.921, "high": 0.926, "low": 0.906, "volume": 338109.0, "amount": 0.0}, {"date": "2024-08-05", "open": 0.916, "close": 0.889, "high": 0.916, "low": 0.882, "volume": 338477.0, "amount": 0.0}, {"date": "2024-08-06", "open": 0.896, "close": 0.889, "high": 0.903, "low": 0.886, "volume": 113804.0, "amount": 0.0}, {"date": "2024-08-07", "open": 0.89, "close": 0.899, "high": 0.906, "low": 0.89, "volume": 61653.0, "amount": 0.0}, {"date": "2024-08-08", "open": 0.897, "close": 0.894, "high": 0.901, "low": 0.889, "volume": 53476.0, "amount": 0.0}, {"date": "2024-08-09", "open": 0.894, "close": 0.898, "high": 0.908, "low": 0.894, "volume": 100559.0, "amount": 0.0}, {"date": "2024-08-12", "open": 0.903, "close": 0.905, "high": 0.907, "low": 0.898, "volume": 38514.0, "amount": 0.0}, {"date": "2024-08-13", "open": 0.905, "close": 0.912, "high": 0.918, "low": 0.905, "volume": 50359.0, "amount": 0.0}, {"date": "2024-08-14", "open": 0.913, "close": 0.906, "high": 0.915, "low": 0.905, "volume": 93974.0, "amount": 0.0}, {"date": "2024-08-15", "open": 0.903, "close": 0.917, "high": 0.924, "low": 0.9, "volume": 185976.0, "amount": 0.0}, {"date": "2024-08-16", "open": 0.92, "close": 0.932, "high": 0.934, "low": 0.92, "volume": 152270.0, "amount": 0.0}, {"date": "2024-08-19", "open": 0.932, "close": 0.931, "high": 0.937, "low": 0.928, "volume": 123959.0, "amount": 0.0}, {"date": "2024-08-20", "open": 0.93, "close": 0.921, "high": 0.931, "low": 0.919, "volume": 31380.0, "amount": 0.0}, {"date": "2024-08-21", "open": 0.921, "close": 0.92, "high": 0.921, "low": 0.914, "volume": 54584.0, "amount": 0.0}, {"date": "2024-08-22", "open": 0.923, "close": 0.931, "high": 0.931, "low": 0.916, "volume": 64995.0, "amount": 0.0}, {"date": "2024-08-23", "open": 0.933, "close": 0.925, "high": 0.933, "low": 0.92, "volume": 53411.0, "amount": 0.0}, {"date": "2024-08-26", "open": 0.925, "close": 0.937, "high": 0.937, "low": 0.925, "volume": 144481.0, "amount": 0.0}, {"date": "2024-08-27", "open": 0.932, "close": 0.949, "high": 0.951, "low": 0.932, "volume": 620597.0, "amount": 0.0}, {"date": "2024-08-28", "open": 0.948, "close": 0.942, "high": 0.95, "low": 0.937, "volume": 113677.0, "amount": 0.0}, {"date": "2024-08-29", "open": 0.942, "close": 0.932, "high": 0.942, "low": 0.927, "volume": 95234.0, "amount": 0.0}, {"date": "2024-08-30", "open": 0.932, "close": 0.938, "high": 0.945, "low": 0.932, "volume": 301880.0, "amount": 0.0}, {"date": "2024-09-02", "open": 0.936, "close": 0.928, "high": 0.936, "low": 0.924, "volume": 85177.0, "amount": 0.0}, {"date": "2024-09-03", "open": 0.928, "close": 0.918, "high": 0.932, "low": 0.915, "volume": 83398.0, "amount": 0.0}, {"date": "2024-09-04", "open": 0.91, "close": 0.901, "high": 0.91, "low": 0.899, "volume": 62878.0, "amount": 0.0}, {"date": "2024-09-05", "open": 0.905, "close": 0.896, "high": 0.907, "low": 0.893, "volume": 32167.0, "amount": 0.0}, {"date": "2024-09-06", "open": 0.915, "close": 0.893, "high": 0.915, "low": 0.892, "volume": 16380.0, "amount": 0.0}, {"date": "2024-09-09", "open": 0.891, "close": 0.872, "high": 0.897, "low": 0.87, "volume": 98922.0, "amount": 0.0}, {"date": "2024-09-10", "open": 0.878, "close": 0.875, "high": 0.882, "low": 0.87, "volume": 52674.0, "amount": 0.0}, {"date": "2024-09-11", "open": 0.855, "close": 0.862, "high": 0.862, "low": 0.852, "volume": 47314.0, "amount": 0.0}, {"date": "2024-09-12", "open": 0.862, "close": 0.87, "high": 0.872, "low": 0.855, "volume": 48042.0, "amount": 0.0}, {"date": "2024-09-13", "open": 0.869, "close": 0.878, "high": 0.884, "low": 0.868, "volume": 33389.0, "amount": 0.0}, {"date": "2024-09-18", "open": 0.884, "close": 0.892, "high": 0.893, "low": 0.883, "volume": 23053.0, "amount": 0.0}, {"date": "2024-09-19", "open": 0.893, "close": 0.905, "high": 0.909, "low": 0.893, "volume": 45499.0, "amount": 0.0}, {"date": "2024-09-20", "open": 0.911, "close": 0.911, "high": 0.915, "low": 0.903, "volume": 45284.0, "amount": 0.0}, {"date": "2024-09-23", "open": 0.911, "close": 0.925, "high": 0.929, "low": 0.911, "volume": 61469.0, "amount": 0.0}, {"date": "2024-09-24", "open": 0.934, "close": 0.96, "high": 0.963, "low": 0.934, "volume": 275540.0, "amount": 0.0}, {"date": "2024-09-25", "open": 0.974, "close": 0.966, "high": 0.999, "low": 0.964, "volume": 307464.0, "amount": 0.0}, {"date": "2024-09-26", "open": 0.966, "close": 0.985, "high": 0.985, "low": 0.966, "volume": 261897.0, "amount": 0.0}, {"date": "2024-09-27", "open": 0.989, "close": 1.005, "high": 1.008, "low": 0.989, "volume": 153823.0, "amount": 0.0}, {"date": "2024-09-30", "open": 1.016, "close": 1.045, "high": 1.111, "low": 1.016, "volume": 534521.0, "amount": 0.0}, {"date": "2024-10-08", "open": 1.152, "close": 1.058, "high": 1.155, "low": 1.011, "volume": 671118.0, "amount": 0.0}, {"date": "2024-10-09", "open": 1.077, "close": 0.997, "high": 1.077, "low": 0.991, "volume": 279397.0, "amount": 0.0}, {"date": "2024-10-10", "open": 1.014, "close": 1.053, "high": 1.068, "low": 1.003, "volume": 546055.0, "amount": 0.0}, {"date": "2024-10-11", "open": 1.053, "close": 1.025, "high": 1.139, "low": 1.025, "volume": 1185195.0, "amount": 0.0}, {"date": "2024-10-14", "open": 1.043, "close": 1.062, "high": 1.094, "low": 1.041, "volume": 1103932.0, "amount": 0.0}, {"date": "2024-10-15", "open": 1.064, "close": 1.026, "high": 1.069, "low": 1.023, "volume": 355819.0, "amount": 0.0}, {"date": "2024-10-16", "open": 1.014, "close": 1.048, "high": 1.061, "low": 1.014, "volume": 570273.0, "amount": 0.0}, {"date": "2024-10-17", "open": 1.056, "close": 1.032, "high": 1.108, "low": 1.031, "volume": 834443.0, "amount": 0.0}, {"date": "2024-10-18", "open": 1.04, "close": 1.052, "high": 1.063, "low": 1.026, "volume": 697493.0, "amount": 0.0}, {"date": "2024-10-21", "open": 1.053, "close": 1.05, "high": 1.066, "low": 1.046, "volume": 282054.0, "amount": 0.0}, {"date": "2024-10-22", "open": 1.058, "close": 1.054, "high": 1.06, "low": 1.051, "volume": 174126.0, "amount": 0.0}, {"date": "2024-10-23", "open": 1.057, "close": 1.062, "high": 1.068, "low": 1.054, "volume": 240279.0, "amount": 0.0}, {"date": "2024-10-24", "open": 1.062, "close": 1.062, "high": 1.063, "low": 1.056, "volume": 113313.0, "amount": 0.0}, {"date": "2024-10-25", "open": 1.063, "close": 1.057, "high": 1.069, "low": 1.056, "volume": 137548.0, "amount": 0.0}, {"date": "2024-10-28", "open": 1.064, "close": 1.059, "high": 1.064, "low": 1.052, "volume": 139803.0, "amount": 0.0}, {"date": "2024-10-29", "open": 1.059, "close": 1.046, "high": 1.063, "low": 1.046, "volume": 110836.0, "amount": 0.0}, {"date": "2024-10-30", "open": 1.047, "close": 1.029, "high": 1.053, "low": 1.028, "volume": 149623.0, "amount": 0.0}, {"date": "2024-10-31", "open": 1.027, "close": 1.034, "high": 1.043, "low": 1.027, "volume": 163145.0, "amount": 0.0}, {"date": "2024-11-01", "open": 1.039, "close": 1.045, "high": 1.058, "low": 1.039, "volume": 163266.0, "amount": 0.0}, {"date": "2024-11-04", "open": 1.045, "close": 1.052, "high": 1.052, "low": 1.039, "volume": 124700.0, "amount": 0.0}, {"date": "2024-11-05", "open": 1.051, "close": 1.068, "high": 1.071, "low": 1.05, "volume": 190836.0, "amount": 0.0}, {"date": "2024-11-06", "open": 1.071, "close": 1.057, "high": 1.076, "low": 1.056, "volume": 144636.0, "amount": 0.0}, {"date": "2024-11-07", "open": 1.057, "close": 1.084, "high": 1.086, "low": 1.056, "volume": 154916.0, "amount": 0.0}, {"date": "2024-11-08", "open": 1.094, "close": 1.074, "high": 1.1, "low": 1.071, "volume": 170728.0, "amount": 0.0}, {"date": "2024-11-11", "open": 1.064, "close": 1.058, "high": 1.074, "low": 1.055, "volume": 170856.0, "amount": 0.0}, {"date": "2024-11-12", "open": 1.056, "close": 1.035, "high": 1.07, "low": 1.032, "volume": 119960.0, "amount": 0.0}, {"date": "2024-11-13", "open": 1.034, "close": 1.036, "high": 1.044, "low": 1.029, "volume": 94513.0, "amount": 0.0}, {"date": "2024-11-14", "open": 1.036, "close": 1.02, "high": 1.042, "low": 1.02, "volume": 65345.0, "amount": 0.0}, {"date": "2024-11-15", "open": 1.024, "close": 1.021, "high": 1.029, "low": 1.018, "volume": 125138.0, "amount": 0.0}, {"date": "2024-11-18", "open": 1.025, "close": 1.035, "high": 1.047, "low": 1.024, "volume": 159549.0, "amount": 0.0}, {"date": "2024-11-19", "open": 1.036, "close": 1.038, "high": 1.044, "low": 1.032, "volume": 95502.0, "amount": 0.0}, {"date": "2024-11-20", "open": 1.04, "close": 1.04, "high": 1.043, "low": 1.034, "volume": 46863.0, "amount": 0.0}, {"date": "2024-11-21", "open": 1.039, "close": 1.039, "high": 1.043, "low": 1.038, "volume": 39843.0, "amount": 0.0}, {"date": "2024-11-22", "open": 1.041, "close": 1.006, "high": 1.042, "low": 1.006, "volume": 75854.0, "amount": 0.0}, {"date": "2024-11-25", "open": 1.018, "close": 1.013, "high": 1.019, "low": 1.008, "volume": 27099.0, "amount": 0.0}, {"date": "2024-11-26", "open": 1.013, "close": 1.004, "high": 1.014, "low": 1.003, "volume": 16398.0, "amount": 0.0}, {"date": "2024-11-27", "open": 1.004, "close": 1.006, "high": 1.006, "low": 0.995, "volume": 35404.0, "amount": 0.0}, {"date": "2024-11-28", "open": 1.008, "close": 0.998, "high": 1.01, "low": 0.996, "volume": 22996.0, "amount": 0.0}, {"date": "2024-11-29", "open": 0.998, "close": 0.999, "high": 1.006, "low": 0.992, "volume": 51504.0, "amount": 0.0}, {"date": "2024-12-02", "open": 1.001, "close": 1.006, "high": 1.012, "low": 1.001, "volume": 50272.0, "amount": 0.0}, {"date": "2024-12-03", "open": 1.01, "close": 1.023, "high": 1.028, "low": 1.01, "volume": 87963.0, "amount": 0.0}, {"date": "2024-12-04", "open": 1.023, "close": 1.038, "high": 1.038, "low": 1.019, "volume": 71539.0, "amount": 0.0}, {"date": "2024-12-05", "open": 1.038, "close": 1.032, "high": 1.038, "low": 1.027, "volume": 49142.0, "amount": 0.0}, {"date": "2024-12-06", "open": 1.038, "close": 1.041, "high": 1.048, "low": 1.036, "volume": 78762.0, "amount": 0.0}, {"date": "2024-12-09", "open": 1.042, "close": 1.047, "high": 1.054, "low": 1.038, "volume": 30799.0, "amount": 0.0}, {"date": "2024-12-10", "open": 1.07, "close": 1.056, "high": 1.117, "low": 1.051, "volume": 148170.0, "amount": 0.0}, {"date": "2024-12-11", "open": 1.056, "close": 1.057, "high": 1.065, "low": 1.053, "volume": 65832.0, "amount": 0.0}, {"date": "2024-12-12", "open": 1.056, "close": 1.064, "high": 1.068, "low": 1.054, "volume": 59633.0, "amount": 0.0}, {"date": "2024-12-13", "open": 1.064, "close": 1.04, "high": 1.064, "low": 1.038, "volume": 120974.0, "amount": 0.0}, {"date": "2024-12-16", "open": 1.04, "close": 1.034, "high": 1.041, "low": 1.033, "volume": 37075.0, "amount": 0.0}, {"date": "2024-12-17", "open": 1.034, "close": 1.038, "high": 1.05, "low": 1.032, "volume": 126571.0, "amount": 0.0}, {"date": "2024-12-18", "open": 1.044, "close": 1.044, "high": 1.052, "low": 1.043, "volume": 53206.0, "amount": 0.0}, {"date": "2024-12-19", "open": 1.036, "close": 1.042, "high": 1.043, "low": 1.034, "volume": 23213.0, "amount": 0.0}, {"date": "2024-12-20", "open": 1.042, "close": 1.034, "high": 1.042, "low": 1.031, "volume": 49575.0, "amount": 0.0}, {"date": "2024-12-23", "open": 1.036, "close": 1.041, "high": 1.046, "low": 1.034, "volume": 63394.0, "amount": 0.0}, {"date": "2024-12-24", "open": 1.044, "close": 1.059, "high": 1.074, "low": 1.04, "volume": 129885.0, "amount": 0.0}, {"date": "2024-12-25", "open": 1.06, "close": 1.106, "high": 1.151, "low": 1.06, "volume": 1340588.0, "amount": 0.0}, {"date": "2024-12-26", "open": 1.118, "close": 1.222, "high": 1.222, "low": 1.117, "volume": 2948753.0, "amount": 0.0}, {"date": "2024-12-27", "open": 1.094, "close": 1.094, "high": 1.094, "low": 1.094, "volume": 153303.0, "amount": 0.0}, {"date": "2024-12-30", "open": 1.059, "close": 1.072, "high": 1.079, "low": 1.059, "volume": 2693616.0, "amount": 0.0}, {"date": "2024-12-31", "open": 1.086, "close": 1.064, "high": 1.101, "low": 1.063, "volume": 2108340.0, "amount": 0.0}, {"date": "2025-01-02", "open": 1.071, "close": 1.05, "high": 1.073, "low": 1.043, "volume": 604366.0, "amount": 0.0}, {"date": "2025-01-03", "open": 1.061, "close": 1.054, "high": 1.064, "low": 1.05, "volume": 389077.0, "amount": 0.0}, {"date": "2025-01-06", "open": 1.057, "close": 1.052, "high": 1.069, "low": 1.051, "volume": 241522.0, "amount": 0.0}, {"date": "2025-01-07", "open": 1.053, "close": 1.04, "high": 1.055, "low": 1.036, "volume": 230561.0, "amount": 0.0}, {"date": "2025-01-08", "open": 1.044, "close": 1.038, "high": 1.058, "low": 1.033, "volume": 306509.0, "amount": 0.0}, {"date": "2025-01-09", "open": 1.04, "close": 1.028, "high": 1.044, "low": 1.025, "volume": 196865.0, "amount": 0.0}, {"date": "2025-01-10", "open": 1.028, "close": 1.017, "high": 1.042, "low": 1.016, "volume": 413781.0, "amount": 0.0}, {"date": "2025-01-13", "open": 1.014, "close": 1.018, "high": 1.021, "low": 1.011, "volume": 342746.0, "amount": 0.0}, {"date": "2025-01-14", "open": 1.018, "close": 1.029, "high": 1.031, "low": 1.018, "volume": 378103.0, "amount": 0.0}, {"date": "2025-01-15", "open": 1.035, "close": 1.028, "high": 1.038, "low": 1.024, "volume": 262386.0, "amount": 0.0}, {"date": "2025-01-16", "open": 1.03, "close": 1.034, "high": 1.038, "low": 1.026, "volume": 281279.0, "amount": 0.0}, {"date": "2025-01-17", "open": 1.033, "close": 1.027, "high": 1.036, "low": 1.024, "volume": 142083.0, "amount": 0.0}, {"date": "2025-01-20", "open": 1.03, "close": 1.03, "high": 1.035, "low": 1.026, "volume": 201496.0, "amount": 0.0}, {"date": "2025-01-21", "open": 1.033, "close": 1.027, "high": 1.036, "low": 1.025, "volume": 148650.0, "amount": 0.0}, {"date": "2025-01-22", "open": 1.027, "close": 1.02, "high": 1.028, "low": 1.017, "volume": 121743.0, "amount": 0.0}, {"date": "2025-01-23", "open": 1.029, "close": 1.03, "high": 1.036, "low": 1.028, "volume": 158589.0, "amount": 0.0}, {"date": "2025-01-24", "open": 1.028, "close": 1.037, "high": 1.038, "low": 1.028, "volume": 145022.0, "amount": 0.0}, {"date": "2025-01-27", "open": 1.035, "close": 1.042, "high": 1.047, "low": 1.035, "volume": 182264.0, "amount": 0.0}, {"date": "2025-02-05", "open": 1.044, "close": 1.042, "high": 1.047, "low": 1.036, "volume": 177000.0, "amount": 0.0}, {"date": "2025-02-06", "open": 1.042, "close": 1.047, "high": 1.049, "low": 1.042, "volume": 191965.0, "amount": 0.0}, {"date": "2025-02-07", "open": 1.048, "close": 1.046, "high": 1.05, "low": 1.042, "volume": 211841.0, "amount": 0.0}, {"date": "2025-02-10", "open": 1.045, "close": 1.048, "high": 1.055, "low": 1.045, "volume": 176294.0, "amount": 0.0}, {"date": "2025-02-11", "open": 1.051, "close": 1.052, "high": 1.058, "low": 1.05, "volume": 282878.0, "amount": 0.0}, {"date": "2025-02-12", "open": 1.053, "close": 1.062, "high": 1.064, "low": 1.053, "volume": 218996.0, "amount": 0.0}, {"date": "2025-02-13", "open": 1.065, "close": 1.067, "high": 1.068, "low": 1.059, "volume": 170869.0, "amount": 0.0}, {"date": "2025-02-14", "open": 1.068, "close": 1.07, "high": 1.073, "low": 1.057, "volume": 196243.0, "amount": 0.0}, {"date": "2025-02-17", "open": 1.073, "close": 1.075, "high": 1.079, "low": 1.067, "volume": 158811.0, "amount": 0.0}, {"date": "2025-02-18", "open": 1.078, "close": 1.074, "high": 1.087, "low": 1.074, "volume": 219079.0, "amount": 0.0}, {"date": "2025-02-19", "open": 1.074, "close": 1.074, "high": 1.084, "low": 1.072, "volume": 145205.0, "amount": 0.0}, {"date": "2025-02-20", "open": 1.073, "close": 1.073, "high": 1.076, "low": 1.065, "volume": 164538.0, "amount": 0.0}, {"date": "2025-02-21", "open": 1.076, "close": 1.079, "high": 1.082, "low": 1.074, "volume": 127481.0, "amount": 0.0}, {"date": "2025-02-24", "open": 1.08, "close": 1.08, "high": 1.084, "low": 1.072, "volume": 133424.0, "amount": 0.0}, {"date": "2025-02-25", "open": 1.079, "close": 1.066, "high": 1.079, "low": 1.065, "volume": 46395.0, "amount": 0.0}, {"date": "2025-02-26", "open": 1.066, "close": 1.076, "high": 1.085, "low": 1.066, "volume": 126559.0, "amount": 0.0}, {"date": "2025-02-27", "open": 1.075, "close": 1.077, "high": 1.085, "low": 1.07, "volume": 102012.0, "amount": 0.0}, {"date": "2025-02-28", "open": 1.076, "close": 1.066, "high": 1.078, "low": 1.063, "volume": 44052.0, "amount": 0.0}, {"date": "2025-03-03", "open": 1.074, "close": 1.073, "high": 1.079, "low": 1.066, "volume": 39205.0, "amount": 0.0}, {"date": "2025-03-04", "open": 1.07, "close": 1.073, "high": 1.073, "low": 1.059, "volume": 42852.0, "amount": 0.0}, {"date": "2025-03-05", "open": 1.073, "close": 1.083, "high": 1.086, "low": 1.073, "volume": 158171.0, "amount": 0.0}, {"date": "2025-03-06", "open": 1.09, "close": 1.088, "high": 1.092, "low": 1.079, "volume": 110578.0, "amount": 0.0}, {"date": "2025-03-07", "open": 1.084, "close": 1.089, "high": 1.092, "low": 1.081, "volume": 53845.0, "amount": 0.0}, {"date": "2025-03-10", "open": 1.086, "close": 1.086, "high": 1.094, "low": 1.078, "volume": 112516.0, "amount": 0.0}, {"date": "2025-03-11", "open": 1.081, "close": 1.091, "high": 1.092, "low": 1.078, "volume": 73940.0, "amount": 0.0}, {"date": "2025-03-12", "open": 1.101, "close": 1.092, "high": 1.101, "low": 1.087, "volume": 73292.0, "amount": 0.0}, {"date": "2025-03-13", "open": 1.088, "close": 1.087, "high": 1.096, "low": 1.08, "volume": 129942.0, "amount": 0.0}, {"date": "2025-03-14", "open": 1.09, "close": 1.106, "high": 1.111, "low": 1.088, "volume": 213346.0, "amount": 0.0}, {"date": "2025-03-17", "open": 1.104, "close": 1.11, "high": 1.12, "low": 1.103, "volume": 151230.0, "amount": 0.0}, {"date": "2025-03-18", "open": 1.11, "close": 1.116, "high": 1.118, "low": 1.11, "volume": 64810.0, "amount": 0.0}, {"date": "2025-03-19", "open": 1.114, "close": 1.117, "high": 1.12, "low": 1.113, "volume": 58854.0, "amount": 0.0}, {"date": "2025-03-20", "open": 1.117, "close": 1.111, "high": 1.12, "low": 1.11, "volume": 187235.0, "amount": 0.0}, {"date": "2025-03-21", "open": 1.11, "close": 1.098, "high": 1.113, "low": 1.092, "volume": 59954.0, "amount": 0.0}, {"date": "2025-03-24", "open": 1.098, "close": 1.103, "high": 1.107, "low": 1.093, "volume": 65069.0, "amount": 0.0}, {"date": "2025-03-25", "open": 1.099, "close": 1.093, "high": 1.102, "low": 1.09, "volume": 42660.0, "amount": 0.0}, {"date": "2025-03-26", "open": 1.096, "close": 1.091, "high": 1.098, "low": 1.086, "volume": 31545.0, "amount": 0.0}, {"date": "2025-03-27", "open": 1.09, "close": 1.096, "high": 1.1, "low": 1.09, "volume": 33071.0, "amount": 0.0}, {"date": "2025-03-28", "open": 1.099, "close": 1.092, "high": 1.101, "low": 1.086, "volume": 37485.0, "amount": 0.0}, {"date": "2025-03-31", "open": 1.096, "close": 1.088, "high": 1.101, "low": 1.084, "volume": 73222.0, "amount": 0.0}, {"date": "2025-04-01", "open": 1.087, "close": 1.102, "high": 1.102, "low": 1.087, "volume": 45543.0, "amount": 0.0}, {"date": "2025-04-02", "open": 1.102, "close": 1.11, "high": 1.11, "low": 1.098, "volume": 50398.0, "amount": 0.0}, {"date": "2025-04-03", "open": 1.109, "close": 1.097, "high": 1.109, "low": 1.091, "volume": 66295.0, "amount": 0.0}, {"date": "2025-04-07", "open": 1.042, "close": 0.985, "high": 1.07, "low": 0.983, "volume": 143707.0, "amount": 0.0}, {"date": "2025-04-08", "open": 0.984, "close": 0.996, "high": 1.006, "low": 0.984, "volume": 89195.0, "amount": 0.0}, {"date": "2025-04-09", "open": 0.985, "close": 0.999, "high": 1.005, "low": 0.97, "volume": 97519.0, "amount": 0.0}, {"date": "2025-04-10", "open": 1.024, "close": 1.03, "high": 1.049, "low": 1.024, "volume": 130113.0, "amount": 0.0}, {"date": "2025-04-11", "open": 1.017, "close": 1.035, "high": 1.042, "low": 1.017, "volume": 78848.0, "amount": 0.0}, {"date": "2025-04-14", "open": 1.045, "close": 1.059, "high": 1.06, "low": 1.045, "volume": 59289.0, "amount": 0.0}, {"date": "2025-04-15", "open": 1.06, "close": 1.062, "high": 1.065, "low": 1.056, "volume": 40363.0, "amount": 0.0}, {"date": "2025-04-16", "open": 1.058, "close": 1.054, "high": 1.066, "low": 1.048, "volume": 38314.0, "amount": 0.0}, {"date": "2025-04-17", "open": 1.054, "close": 1.059, "high": 1.063, "low": 1.053, "volume": 40753.0, "amount": 0.0}, {"date": "2025-04-18", "open": 1.06, "close": 1.084, "high": 1.143, "low": 1.058, "volume": 4076548.0, "amount": 0.0}, {"date": "2025-04-21", "open": 1.086, "close": 1.065, "high": 1.142, "low": 1.06, "volume": 2575470.0, "amount": 0.0}, {"date": "2025-04-22", "open": 1.065, "close": 1.06, "high": 1.071, "low": 1.053, "volume": 353156.0, "amount": 0.0}, {"date": "2025-04-23", "open": 1.074, "close": 1.069, "high": 1.076, "low": 1.067, "volume": 189606.0, "amount": 0.0}, {"date": "2025-04-24", "open": 1.073, "close": 1.067, "high": 1.075, "low": 1.066, "volume": 69233.0, "amount": 0.0}, {"date": "2025-04-25", "open": 1.068, "close": 1.074, "high": 1.077, "low": 1.068, "volume": 109618.0, "amount": 0.0}, {"date": "2025-04-28", "open": 1.08, "close": 1.081, "high": 1.085, "low": 1.071, "volume": 90668.0, "amount": 0.0}, {"date": "2025-04-29", "open": 1.085, "close": 1.074, "high": 1.085, "low": 1.072, "volume": 82636.0, "amount": 0.0}, {"date": "2025-04-30", "open": 1.076, "close": 1.07, "high": 1.078, "low": 1.064, "volume": 71290.0, "amount": 0.0}, {"date": "2025-05-06", "open": 1.074, "close": 1.076, "high": 1.076, "low": 1.066, "volume": 90018.0, "amount": 0.0}, {"date": "2025-05-07", "open": 1.081, "close": 1.087, "high": 1.092, "low": 1.08, "volume": 128874.0, "amount": 0.0}, {"date": "2025-05-08", "open": 1.086, "close": 1.083, "high": 1.089, "low": 1.081, "volume": 56412.0, "amount": 0.0}, {"date": "2025-05-09", "open": 1.085, "close": 1.091, "high": 1.092, "low": 1.082, "volume": 69397.0, "amount": 0.0}, {"date": "2025-05-12", "open": 1.095, "close": 1.102, "high": 1.103, "low": 1.094, "volume": 91535.0, "amount": 0.0}, {"date": "2025-05-13", "open": 1.107, "close": 1.117, "high": 1.117, "low": 1.103, "volume": 88826.0, "amount": 0.0}, {"date": "2025-05-14", "open": 1.122, "close": 1.135, "high": 1.151, "low": 1.115, "volume": 165744.0, "amount": 0.0}, {"date": "2025-05-15", "open": 1.136, "close": 1.132, "high": 1.142, "low": 1.129, "volume": 108631.0, "amount": 0.0}, {"date": "2025-05-16", "open": 1.13, "close": 1.13, "high": 1.133, "low": 1.121, "volume": 53943.0, "amount": 0.0}, {"date": "2025-05-19", "open": 1.13, "close": 1.136, "high": 1.14, "low": 1.129, "volume": 44698.0, "amount": 0.0}, {"date": "2025-05-20", "open": 1.137, "close": 1.155, "high": 1.155, "low": 1.137, "volume": 84883.0, "amount": 0.0}, {"date": "2025-05-21", "open": 1.159, "close": 1.162, "high": 1.167, "low": 1.152, "volume": 96151.0, "amount": 0.0}, {"date": "2025-05-22", "open": 1.162, "close": 1.162, "high": 1.169, "low": 1.158, "volume": 88059.0, "amount": 0.0}, {"date": "2025-05-23", "open": 1.161, "close": 1.156, "high": 1.168, "low": 1.156, "volume": 64195.0, "amount": 0.0}, {"date": "2025-05-26", "open": 1.16, "close": 1.159, "high": 1.17, "low": 1.155, "volume": 77943.0, "amount": 0.0}, {"date": "2025-05-27", "open": 1.159, "close": 1.156, "high": 1.164, "low": 1.154, "volume": 52564.0, "amount": 0.0}, {"date": "2025-05-28", "open": 1.163, "close": 1.163, "high": 1.166, "low": 1.157, "volume": 58524.0, "amount": 0.0}, {"date": "2025-05-29", "open": 1.164, "close": 1.166, "high": 1.168, "low": 1.164, "volume": 55026.0, "amount": 0.0}, {"date": "2025-05-30", "open": 1.166, "close": 1.165, "high": 1.172, "low": 1.162, "volume": 94680.0, "amount": 0.0}, {"date": "2025-06-03", "open": 1.165, "close": 1.172, "high": 1.173, "low": 1.162, "volume": 78510.0, "amount": 0.0}, {"date": "2025-06-04", "open": 1.174, "close": 1.171, "high": 1.174, "low": 1.167, "volume": 59775.0, "amount": 0.0}, {"date": "2025-06-05", "open": 1.172, "close": 1.164, "high": 1.173, "low": 1.161, "volume": 71749.0, "amount": 0.0}, {"date": "2025-06-06", "open": 1.165, "close": 1.167, "high": 1.171, "low": 1.162, "volume": 57404.0, "amount": 0.0}, {"date": "2025-06-09", "open": 1.168, "close": 1.169, "high": 1.171, "low": 1.165, "volume": 42342.0, "amount": 0.0}, {"date": "2025-06-10", "open": 1.171, "close": 1.189, "high": 1.193, "low": 1.171, "volume": 68433.0, "amount": 0.0}, {"date": "2025-06-11", "open": 1.201, "close": 1.212, "high": 1.212, "low": 1.191, "volume": 74770.0, "amount": 0.0}, {"date": "2025-06-12", "open": 1.209, "close": 1.207, "high": 1.212, "low": 1.204, "volume": 61107.0, "amount": 0.0}, {"date": "2025-06-13", "open": 1.206, "close": 1.22, "high": 1.224, "low": 1.204, "volume": 106931.0, "amount": 0.0}, {"date": "2025-06-16", "open": 1.219, "close": 1.224, "high": 1.224, "low": 1.213, "volume": 64433.0, "amount": 0.0}, {"date": "2025-06-17", "open": 1.227, "close": 1.222, "high": 1.229, "low": 1.219, "volume": 65164.0, "amount": 0.0}, {"date": "2025-06-18", "open": 1.222, "close": 1.218, "high": 1.231, "low": 1.212, "volume": 58353.0, "amount": 0.0}, {"date": "2025-06-19", "open": 1.216, "close": 1.188, "high": 1.222, "low": 1.187, "volume": 110574.0, "amount": 0.0}, {"date": "2025-06-20", "open": 1.189, "close": 1.206, "high": 1.213, "low": 1.189, "volume": 147548.0, "amount": 0.0}, {"date": "2025-06-23", "open": 1.208, "close": 1.218, "high": 1.218, "low": 1.197, "volume": 102232.0, "amount": 0.0}, {"date": "2025-06-24", "open": 1.221, "close": 1.227, "high": 1.227, "low": 1.213, "volume": 87867.0, "amount": 0.0}, {"date": "2025-06-25", "open": 1.229, "close": 1.226, "high": 1.231, "low": 1.218, "volume": 111810.0, "amount": 0.0}, {"date": "2025-06-26", "open": 1.227, "close": 1.221, "high": 1.228, "low": 1.22, "volume": 31812.0, "amount": 0.0}, {"date": "2025-06-27", "open": 1.223, "close": 1.213, "high": 1.226, "low": 1.209, "volume": 91032.0, "amount": 0.0}, {"date": "2025-06-30", "open": 1.214, "close": 1.208, "high": 1.215, "low": 1.202, "volume": 119177.0, "amount": 0.0}, {"date": "2025-07-01", "open": 1.217, "close": 1.21, "high": 1.219, "low": 1.207, "volume": 81163.0, "amount": 0.0}, {"date": "2025-07-02", "open": 1.211, "close": 1.227, "high": 1.229, "low": 1.211, "volume": 141441.0, "amount": 0.0}, {"date": "2025-07-03", "open": 1.229, "close": 1.228, "high": 1.236, "low": 1.22, "volume": 104969.0, "amount": 0.0}, {"date": "2025-07-04", "open": 1.229, "close": 1.224, "high": 1.229, "low": 1.223, "volume": 86831.0, "amount": 0.0}, {"date": "2025-07-07", "open": 1.224, "close": 1.227, "high": 1.227, "low": 1.221, "volume": 41720.0, "amount": 0.0}, {"date": "2025-07-08", "open": 1.228, "close": 1.226, "high": 1.233, "low": 1.223, "volume": 53131.0, "amount": 0.0}, {"date": "2025-07-09", "open": 1.228, "close": 1.227, "high": 1.229, "low": 1.221, "volume": 56721.0, "amount": 0.0}, {"date": "2025-07-10", "open": 1.229, "close": 1.247, "high": 1.25, "low": 1.229, "volume": 221937.0, "amount": 0.0}, {"date": "2025-07-11", "open": 1.248, "close": 1.265, "high": 1.273, "low": 1.248, "volume": 217804.0, "amount": 0.0}, {"date": "2025-07-14", "open": 1.269, "close": 1.264, "high": 1.274, "low": 1.261, "volume": 167345.0, "amount": 0.0}, {"date": "2025-07-15", "open": 1.265, "close": 1.259, "high": 1.271, "low": 1.252, "volume": 167784.0, "amount": 0.0}, {"date": "2025-07-16", "open": 1.259, "close": 1.262, "high": 1.267, "low": 1.256, "volume": 148260.0, "amount": 0.0}, {"date": "2025-07-17", "open": 1.265, "close": 1.253, "high": 1.265, "low": 1.251, "volume": 251844.0, "amount": 0.0}, {"date": "2025-07-18", "open": 1.256, "close": 1.258, "high": 1.261, "low": 1.253, "volume": 122448.0, "amount": 0.0}, {"date": "2025-07-21", "open": 1.262, "close": 1.277, "high": 1.277, "low": 1.261, "volume": 121850.0, "amount": 0.0}, {"date": "2025-07-22", "open": 1.279, "close": 1.294, "high": 1.299, "low": 1.27, "volume": 181943.0, "amount": 0.0}, {"date": "2025-07-23", "open": 1.323, "close": 1.3, "high": 1.323, "low": 1.295, "volume": 203110.0, "amount": 0.0}, {"date": "2025-07-24", "open": 1.299, "close": 1.317, "high": 1.317, "low": 1.299, "volume": 249189.0, "amount": 0.0}, {"date": "2025-07-25", "open": 1.317, "close": 1.313, "high": 1.326, "low": 1.309, "volume": 192934.0, "amount": 0.0}, {"date": "2025-07-28", "open": 1.313, "close": 1.309, "high": 1.318, "low": 1.305, "volume": 134596.0, "amount": 0.0}, {"date": "2025-07-29", "open": 1.309, "close": 1.305, "high": 1.313, "low": 1.297, "volume": 138389.0, "amount": 0.0}, {"date": "2025-07-30", "open": 1.305, "close": 1.308, "high": 1.317, "low": 1.3, "volume": 206175.0, "amount": 0.0}, {"date": "2025-07-31", "open": 1.307, "close": 1.285, "high": 1.307, "low": 1.283, "volume": 235985.0, "amount": 0.0}, {"date": "2025-08-01", "open": 1.286, "close": 1.28, "high": 1.29, "low": 1.277, "volume": 78157.0, "amount": 0.0}, {"date": "2025-08-04", "open": 1.282, "close": 1.281, "high": 1.282, "low": 1.258, "volume": 147691.0, "amount": 0.0}, {"date": "2025-08-05", "open": 1.283, "close": 1.297, "high": 1.297, "low": 1.281, "volume": 115544.0, "amount": 0.0}, {"date": "2025-08-06", "open": 1.302, "close": 1.299, "high": 1.312, "low": 1.299, "volume": 198778.0, "amount": 0.0}, {"date": "2025-08-07", "open": 1.303, "close": 1.31, "high": 1.31, "low": 1.296, "volume": 155023.0, "amount": 0.0}, {"date": "2025-08-08", "open": 1.312, "close": 1.309, "high": 1.312, "low": 1.304, "volume": 94535.0, "amount": 0.0}, {"date": "2025-08-11", "open": 1.308, "close": 1.306, "high": 1.311, "low": 1.299, "volume": 84367.0, "amount": 0.0}, {"date": "2025-08-12", "open": 1.306, "close": 1.317, "high": 1.32, "low": 1.305, "volume": 105350.0, "amount": 0.0}, {"date": "2025-08-13", "open": 1.318, "close": 1.323, "high": 1.327, "low": 1.316, "volume": 123564.0, "amount": 0.0}, {"date": "2025-08-14", "open": 1.328, "close": 1.317, "high": 1.331, "low": 1.313, "volume": 119339.0, "amount": 0.0}, {"date": "2025-08-15", "open": 1.319, "close": 1.314, "high": 1.32, "low": 1.309, "volume": 105867.0, "amount": 0.0}, {"date": "2025-08-18", "open": 1.314, "close": 1.313, "high": 1.318, "low": 1.31, "volume": 130240.0, "amount": 0.0}, {"date": "2025-08-19", "open": 1.314, "close": 1.308, "high": 1.315, "low": 1.307, "volume": 72830.0, "amount": 0.0}, {"date": "2025-08-20", "open": 1.306, "close": 1.305, "high": 1.306, "low": 1.294, "volume": 92754.0, "amount": 0.0}, {"date": "2025-08-21", "open": 1.307, "close": 1.307, "high": 1.313, "low": 1.305, "volume": 76364.0, "amount": 0.0}, {"date": "2025-08-22", "open": 1.307, "close": 1.303, "high": 1.312, "low": 1.3, "volume": 120500.0, "amount": 0.0}, {"date": "2025-08-25", "open": 1.306, "close": 1.31, "high": 1.315, "low": 1.306, "volume": 163070.0, "amount": 0.0}, {"date": "2025-08-26", "open": 1.31, "close": 1.3, "high": 1.31, "low": 1.298, "volume": 77280.0, "amount": 0.0}, {"date": "2025-08-27", "open": 1.301, "close": 1.282, "high": 1.304, "low": 1.281, "volume": 127445.0, "amount": 0.0}, {"date": "2025-08-28", "open": 1.282, "close": 1.286, "high": 1.294, "low": 1.279, "volume": 108348.0, "amount": 0.0}, {"date": "2025-08-29", "open": 1.286, "close": 1.278, "high": 1.294, "low": 1.276, "volume": 117342.0, "amount": 0.0}, {"date": "2025-09-01", "open": 1.278, "close": 1.27, "high": 1.278, "low": 1.268, "volume": 86976.0, "amount": 0.0}, {"date": "2025-09-02", "open": 1.274, "close": 1.273, "high": 1.278, "low": 1.267, "volume": 120560.0, "amount": 0.0}, {"date": "2025-09-03", "open": 1.276, "close": 1.268, "high": 1.278, "low": 1.265, "volume": 93110.0, "amount": 0.0}, {"date": "2025-09-04", "open": 1.271, "close": 1.258, "high": 1.272, "low": 1.25, "volume": 118175.0, "amount": 0.0}, {"date": "2025-09-05", "open": 1.258, "close": 1.272, "high": 1.274, "low": 1.258, "volume": 116428.0, "amount": 0.0}, {"date": "2025-09-08", "open": 1.272, "close": 1.28, "high": 1.28, "low": 1.267, "volume": 79666.0, "amount": 0.0}, {"date": "2025-09-09", "open": 1.279, "close": 1.282, "high": 1.287, "low": 1.277, "volume": 103484.0, "amount": 0.0}, {"date": "2025-09-10", "open": 1.282, "close": 1.3, "high": 1.303, "low": 1.282, "volume": 149804.0, "amount": 0.0}, {"date": "2025-09-11", "open": 1.304, "close": 1.305, "high": 1.308, "low": 1.294, "volume": 154703.0, "amount": 0.0}, {"date": "2025-09-12", "open": 1.309, "close": 1.303, "high": 1.313, "low": 1.301, "volume": 118022.0, "amount": 0.0}, {"date": "2025-09-15", "open": 1.309, "close": 1.299, "high": 1.309, "low": 1.297, "volume": 96960.0, "amount": 0.0}, {"date": "2025-09-16", "open": 1.299, "close": 1.292, "high": 1.307, "low": 1.289, "volume": 69507.0, "amount": 0.0}, {"date": "2025-09-17", "open": 1.295, "close": 1.292, "high": 1.298, "low": 1.288, "volume": 72579.0, "amount": 0.0}, {"date": "2025-09-18", "open": 1.293, "close": 1.274, "high": 1.293, "low": 1.27, "volume": 111031.0, "amount": 0.0}, {"date": "2025-09-19", "open": 1.276, "close": 1.278, "high": 1.284, "low": 1.274, "volume": 65013.0, "amount": 0.0}, {"date": "2025-09-22", "open": 1.279, "close": 1.259, "high": 1.279, "low": 1.255, "volume": 86348.0, "amount": 0.0}, {"date": "2025-09-23", "open": 1.26, "close": 1.254, "high": 1.263, "low": 1.249, "volume": 59309.0, "amount": 0.0}, {"date": "2025-09-24", "open": 1.254, "close": 1.255, "high": 1.267, "low": 1.249, "volume": 62876.0, "amount": 0.0}, {"date": "2025-09-25", "open": 1.255, "close": 1.242, "high": 1.257, "low": 1.24, "volume": 99793.0, "amount": 0.0}, {"date": "2025-09-26", "open": 1.24, "close": 1.248, "high": 1.249, "low": 1.234, "volume": 72409.0, "amount": 0.0}, {"date": "2025-09-29", "open": 1.25, "close": 1.252, "high": 1.257, "low": 1.24, "volume": 79357.0, "amount": 0.0}, {"date": "2025-09-30", "open": 1.252, "close": 1.25, "high": 1.257, "low": 1.244, "volume": 78875.0, "amount": 0.0}, {"date": "2025-10-09", "open": 1.247, "close": 1.249, "high": 1.25, "low": 1.237, "volume": 82352.0, "amount": 0.0}, {"date": "2025-10-10", "open": 1.246, "close": 1.254, "high": 1.26, "low": 1.241, "volume": 82000.0, "amount": 0.0}, {"date": "2025-10-13", "open": 1.244, "close": 1.245, "high": 1.248, "low": 1.231, "volume": 97266.0, "amount": 0.0}, {"date": "2025-10-14", "open": 1.253, "close": 1.261, "high": 1.276, "low": 1.251, "volume": 281413.0, "amount": 0.0}, {"date": "2025-10-15", "open": 1.267, "close": 1.272, "high": 1.274, "low": 1.264, "volume": 129442.0, "amount": 0.0}, {"date": "2025-10-16", "open": 1.273, "close": 1.294, "high": 1.294, "low": 1.27, "volume": 170525.0, "amount": 0.0}, {"date": "2025-10-17", "open": 1.294, "close": 1.278, "high": 1.303, "low": 1.278, "volume": 167122.0, "amount": 0.0}, {"date": "2025-10-20", "open": 1.287, "close": 1.293, "high": 1.293, "low": 1.282, "volume": 89306.0, "amount": 0.0}, {"date": "2025-10-21", "open": 1.294, "close": 1.294, "high": 1.301, "low": 1.293, "volume": 77348.0, "amount": 0.0}, {"date": "2025-10-22", "open": 1.297, "close": 1.291, "high": 1.297, "low": 1.281, "volume": 56890.0, "amount": 0.0}, {"date": "2025-10-23", "open": 1.291, "close": 1.302, "high": 1.305, "low": 1.291, "volume": 92805.0, "amount": 0.0}, {"date": "2025-10-24", "open": 1.302, "close": 1.306, "high": 1.307, "low": 1.3, "volume": 80781.0, "amount": 0.0}, {"date": "2025-10-27", "open": 1.309, "close": 1.315, "high": 1.318, "low": 1.303, "volume": 113149.0, "amount": 0.0}, {"date": "2025-10-28", "open": 1.317, "close": 1.314, "high": 1.32, "low": 1.307, "volume": 136464.0, "amount": 0.0}, {"date": "2025-10-29", "open": 1.318, "close": 1.312, "high": 1.318, "low": 1.31, "volume": 115159.0, "amount": 0.0}, {"date": "2025-10-30", "open": 1.315, "close": 1.309, "high": 1.321, "low": 1.305, "volume": 111265.0, "amount": 0.0}, {"date": "2025-10-31", "open": 1.309, "close": 1.305, "high": 1.311, "low": 1.304, "volume": 40037.0, "amount": 0.0}, {"date": "2025-11-03", "open": 1.306, "close": 1.332, "high": 1.332, "low": 1.306, "volume": 113709.0, "amount": 0.0}, {"date": "2025-11-04", "open": 1.333, "close": 1.331, "high": 1.347, "low": 1.326, "volume": 201201.0, "amount": 0.0}, {"date": "2025-11-05", "open": 1.331, "close": 1.335, "high": 1.335, "low": 1.318, "volume": 111061.0, "amount": 0.0}, {"date": "2025-11-06", "open": 1.338, "close": 1.35, "high": 1.351, "low": 1.337, "volume": 88273.0, "amount": 0.0}, {"date": "2025-11-07", "open": 1.35, "close": 1.357, "high": 1.362, "low": 1.349, "volume": 103526.0, "amount": 0.0}, {"date": "2025-11-10", "open": 1.357, "close": 1.373, "high": 1.375, "low": 1.357, "volume": 95774.0, "amount": 0.0}, {"date": "2025-11-11", "open": 1.376, "close": 1.371, "high": 1.384, "low": 1.365, "volume": 81599.0, "amount": 0.0}, {"date": "2025-11-12", "open": 1.378, "close": 1.394, "high": 1.396, "low": 1.377, "volume": 132342.0, "amount": 0.0}, {"date": "2025-11-13", "open": 1.395, "close": 1.387, "high": 1.395, "low": 1.377, "volume": 190392.0, "amount": 0.0}, {"date": "2025-11-14", "open": 1.385, "close": 1.368, "high": 1.385, "low": 1.368, "volume": 112739.0, "amount": 0.0}, {"date": "2025-11-17", "open": 1.368, "close": 1.357, "high": 1.371, "low": 1.355, "volume": 75789.0, "amount": 0.0}, {"date": "2025-11-18", "open": 1.356, "close": 1.332, "high": 1.361, "low": 1.33, "volume": 130185.0, "amount": 0.0}, {"date": "2025-11-19", "open": 1.331, "close": 1.343, "high": 1.348, "low": 1.323, "volume": 120030.0, "amount": 0.0}, {"date": "2025-11-20", "open": 1.338, "close": 1.337, "high": 1.35, "low": 1.335, "volume": 96649.0, "amount": 0.0}, {"date": "2025-11-21", "open": 1.327, "close": 1.312, "high": 1.335, "low": 1.312, "volume": 115935.0, "amount": 0.0}, {"date": "2025-11-24", "open": 1.313, "close": 1.311, "high": 1.318, "low": 1.303, "volume": 76807.0, "amount": 0.0}, {"date": "2025-11-25", "open": 1.311, "close": 1.323, "high": 1.324, "low": 1.311, "volume": 69897.0, "amount": 0.0}, {"date": "2025-11-26", "open": 1.324, "close": 1.322, "high": 1.327, "low": 1.32, "volume": 68204.0, "amount": 0.0}, {"date": "2025-11-27", "open": 1.323, "close": 1.317, "high": 1.325, "low": 1.312, "volume": 91498.0, "amount": 0.0}, {"date": "2025-11-28", "open": 1.318, "close": 1.31, "high": 1.321, "low": 1.309, "volume": 42351.0, "amount": 0.0}, {"date": "2025-12-01", "open": 1.31, "close": 1.319, "high": 1.319, "low": 1.31, "volume": 188655.0, "amount": 0.0}, {"date": "2025-12-02", "open": 1.32, "close": 1.326, "high": 1.332, "low": 1.32, "volume": 128400.0, "amount": 0.0}, {"date": "2025-12-03", "open": 1.329, "close": 1.316, "high": 1.33, "low": 1.314, "volume": 205130.0, "amount": 0.0}, {"date": "2025-12-04", "open": 1.319, "close": 1.324, "high": 1.327, "low": 1.319, "volume": 81811.0, "amount": 0.0}, {"date": "2025-12-05", "open": 1.325, "close": 1.325, "high": 1.326, "low": 1.317, "volume": 78343.0, "amount": 0.0}, {"date": "2025-12-08", "open": 1.326, "close": 1.315, "high": 1.33, "low": 1.314, "volume": 128733.0, "amount": 0.0}, {"date": "2025-12-09", "open": 1.315, "close": 1.295, "high": 1.316, "low": 1.294, "volume": 121142.0, "amount": 0.0}, {"date": "2025-12-10", "open": 1.291, "close": 1.277, "high": 1.295, "low": 1.271, "volume": 111186.0, "amount": 0.0}, {"date": "2025-12-11", "open": 1.288, "close": 1.278, "high": 1.294, "low": 1.274, "volume": 212666.0, "amount": 0.0}, {"date": "2025-12-12", "open": 1.279, "close": 1.281, "high": 1.285, "low": 1.278, "volume": 125639.0, "amount": 0.0}, {"date": "2025-12-15", "open": 1.284, "close": 1.281, "high": 1.286, "low": 1.272, "volume": 73368.0, "amount": 0.0}, {"date": "2025-12-16", "open": 1.289, "close": 1.269, "high": 1.289, "low": 1.266, "volume": 86320.0, "amount": 0.0}, {"date": "2025-12-17", "open": 1.272, "close": 1.274, "high": 1.275, "low": 1.266, "volume": 54276.0, "amount": 0.0}, {"date": "2025-12-18", "open": 1.275, "close": 1.276, "high": 1.278, "low": 1.268, "volume": 68927.0, "amount": 0.0}, {"date": "2025-12-19", "open": 1.289, "close": 1.276, "high": 1.289, "low": 1.274, "volume": 79263.0, "amount": 0.0}, {"date": "2025-12-22", "open": 1.275, "close": 1.27, "high": 1.281, "low": 1.269, "volume": 93170.0, "amount": 0.0}, {"date": "2025-12-23", "open": 1.271, "close": 1.274, "high": 1.283, "low": 1.271, "volume": 134633.0, "amount": 0.0}, {"date": "2025-12-24", "open": 1.282, "close": 1.273, "high": 1.282, "low": 1.268, "volume": 108928.0, "amount": 0.0}, {"date": "2025-12-25", "open": 1.275, "close": 1.272, "high": 1.275, "low": 1.271, "volume": 39903.0, "amount": 0.0}, {"date": "2025-12-26", "open": 1.272, "close": 1.272, "high": 1.273, "low": 1.27, "volume": 30650.0, "amount": 0.0}, {"date": "2025-12-29", "open": 1.272, "close": 1.262, "high": 1.273, "low": 1.26, "volume": 107958.0, "amount": 0.0}, {"date": "2025-12-30", "open": 1.262, "close": 1.264, "high": 1.268, "low": 1.262, "volume": 72977.0, "amount": 0.0}, {"date": "2025-12-31", "open": 1.263, "close": 1.254, "high": 1.263, "low": 1.251, "volume": 72664.0, "amount": 0.0}, {"date": "2026-01-05", "open": 1.254, "close": 1.252, "high": 1.259, "low": 1.25, "volume": 161886.0, "amount": 0.0}, {"date": "2026-01-06", "open": 1.253, "close": 1.261, "high": 1.261, "low": 1.25, "volume": 148797.0, "amount": 0.0}, {"date": "2026-01-07", "open": 1.261, "close": 1.257, "high": 1.262, "low": 1.253, "volume": 92991.0, "amount": 0.0}, {"date": "2026-01-08", "open": 1.257, "close": 1.25, "high": 1.258, "low": 1.249, "volume": 118781.0, "amount": 0.0}, {"date": "2026-01-09", "open": 1.25, "close": 1.255, "high": 1.258, "low": 1.25, "volume": 103335.0, "amount": 0.0}, {"date": "2026-01-12", "open": 1.255, "close": 1.253, "high": 1.256, "low": 1.246, "volume": 129766.0, "amount": 0.0}, {"date": "2026-01-13", "open": 1.252, "close": 1.257, "high": 1.264, "low": 1.252, "volume": 176319.0, "amount": 0.0}, {"date": "2026-01-14", "open": 1.262, "close": 1.258, "high": 1.263, "low": 1.253, "volume": 116392.0, "amount": 0.0}, {"date": "2026-01-15", "open": 1.258, "close": 1.261, "high": 1.27, "low": 1.258, "volume": 166738.0, "amount": 0.0}, {"date": "2026-01-16", "open": 1.262, "close": 1.251, "high": 1.268, "low": 1.249, "volume": 120061.0, "amount": 0.0}, {"date": "2026-01-19", "open": 1.252, "close": 1.244, "high": 1.254, "low": 1.239, "volume": 125874.0, "amount": 0.0}, {"date": "2026-01-20", "open": 1.249, "close": 1.246, "high": 1.25, "low": 1.238, "volume": 111049.0, "amount": 0.0}, {"date": "2026-01-21", "open": 1.246, "close": 1.247, "high": 1.253, "low": 1.245, "volume": 67136.0, "amount": 0.0}, {"date": "2026-01-22", "open": 1.249, "close": 1.261, "high": 1.264, "low": 1.249, "volume": 134790.0, "amount": 0.0}, {"date": "2026-01-23", "open": 1.264, "close": 1.254, "high": 1.268, "low": 1.253, "volume": 101761.0, "amount": 0.0}, {"date": "2026-01-26", "open": 1.254, "close": 1.262, "high": 1.267, "low": 1.251, "volume": 124069.0, "amount": 0.0}, {"date": "2026-01-27", "open": 1.263, "close": 1.272, "high": 1.275, "low": 1.249, "volume": 141423.0, "amount": 0.0}, {"date": "2026-01-28", "open": 1.273, "close": 1.304, "high": 1.307, "low": 1.273, "volume": 278408.0, "amount": 0.0}, {"date": "2026-01-29", "open": 1.305, "close": 1.32, "high": 1.323, "low": 1.303, "volume": 206845.0, "amount": 0.0}, {"date": "2026-01-30", "open": 1.304, "close": 1.307, "high": 1.311, "low": 1.296, "volume": 147372.0, "amount": 0.0}, {"date": "2026-02-02", "open": 1.297, "close": 1.272, "high": 1.3, "low": 1.269, "volume": 170048.0, "amount": 0.0}, {"date": "2026-02-03", "open": 1.278, "close": 1.293, "high": 1.297, "low": 1.278, "volume": 184092.0, "amount": 0.0}, {"date": "2026-02-04", "open": 1.292, "close": 1.314, "high": 1.314, "low": 1.29, "volume": 170847.0, "amount": 0.0}, {"date": "2026-02-05", "open": 1.318, "close": 1.308, "high": 1.318, "low": 1.295, "volume": 145559.0, "amount": 0.0}, {"date": "2026-02-06", "open": 1.304, "close": 1.314, "high": 1.317, "low": 1.295, "volume": 154362.0, "amount": 0.0}, {"date": "2026-02-09", "open": 1.321, "close": 1.325, "high": 1.329, "low": 1.318, "volume": 115957.0, "amount": 0.0}, {"date": "2026-02-10", "open": 1.327, "close": 1.329, "high": 1.33, "low": 1.32, "volume": 102246.0, "amount": 0.0}, {"date": "2026-02-11", "open": 1.329, "close": 1.333, "high": 1.334, "low": 1.321, "volume": 92669.0, "amount": 0.0}, {"date": "2026-02-12", "open": 1.337, "close": 1.331, "high": 1.341, "low": 1.331, "volume": 89284.0, "amount": 0.0}, {"date": "2026-02-13", "open": 1.325, "close": 1.319, "high": 1.327, "low": 1.316, "volume": 100482.0, "amount": 0.0}, {"date": "2026-02-24", "open": 1.331, "close": 1.344, "high": 1.348, "low": 1.331, "volume": 155181.0, "amount": 0.0}, {"date": "2026-02-25", "open": 1.345, "close": 1.345, "high": 1.356, "low": 1.34, "volume": 151517.0, "amount": 0.0}, {"date": "2026-02-26", "open": 1.345, "close": 1.334, "high": 1.348, "low": 1.332, "volume": 106107.0, "amount": 0.0}, {"date": "2026-02-27", "open": 1.333, "close": 1.34, "high": 1.341, "low": 1.329, "volume": 60996.0, "amount": 0.0}, {"date": "2026-03-02", "open": 1.34, "close": 1.343, "high": 1.351, "low": 1.322, "volume": 172409.0, "amount": 0.0}, {"date": "2026-03-03", "open": 1.346, "close": 1.351, "high": 1.365, "low": 1.339, "volume": 298888.0, "amount": 0.0}, {"date": "2026-03-04", "open": 1.349, "close": 1.318, "high": 1.353, "low": 1.314, "volume": 201638.0, "amount": 0.0}, {"date": "2026-03-05", "open": 1.328, "close": 1.335, "high": 1.347, "low": 1.326, "volume": 181953.0, "amount": 0.0}, {"date": "2026-03-06", "open": 1.335, "close": 1.345, "high": 1.348, "low": 1.328, "volume": 109173.0, "amount": 0.0}, {"date": "2026-03-09", "open": 1.352, "close": 1.328, "high": 1.354, "low": 1.327, "volume": 133432.0, "amount": 0.0}, {"date": "2026-03-10", "open": 1.338, "close": 1.336, "high": 1.343, "low": 1.331, "volume": 85645.0, "amount": 0.0}, {"date": "2026-03-11", "open": 1.331, "close": 1.342, "high": 1.343, "low": 1.327, "volume": 74212.0, "amount": 0.0}, {"date": "2026-03-12", "open": 1.341, "close": 1.341, "high": 1.348, "low": 1.332, "volume": 154661.0, "amount": 0.0}, {"date": "2026-03-13", "open": 1.341, "close": 1.324, "high": 1.344, "low": 1.322, "volume": 89006.0, "amount": 0.0}, {"date": "2026-03-16", "open": 1.324, "close": 1.33, "high": 1.334, "low": 1.319, "volume": 67026.0, "amount": 0.0}, {"date": "2026-03-17", "open": 1.331, "close": 1.333, "high": 1.343, "low": 1.331, "volume": 87025.0, "amount": 0.0}, {"date": "2026-03-18", "open": 1.333, "close": 1.336, "high": 1.339, "low": 1.325, "volume": 72400.0, "amount": 0.0}, {"date": "2026-03-19", "open": 1.334, "close": 1.328, "high": 1.337, "low": 1.328, "volume": 63201.0, "amount": 0.0}, {"date": "2026-03-20", "open": 1.328, "close": 1.328, "high": 1.335, "low": 1.32, "volume": 71505.0, "amount": 0.0}, {"date": "2026-03-23", "open": 1.318, "close": 1.289, "high": 1.322, "low": 1.289, "volume": 115861.0, "amount": 0.0}, {"date": "2026-03-24", "open": 1.303, "close": 1.316, "high": 1.319, "low": 1.302, "volume": 89775.0, "amount": 0.0}, {"date": "2026-03-25", "open": 1.322, "close": 1.319, "high": 1.322, "low": 1.308, "volume": 52989.0, "amount": 0.0}, {"date": "2026-03-26", "open": 1.322, "close": 1.32, "high": 1.329, "low": 1.316, "volume": 68969.0, "amount": 0.0}, {"date": "2026-03-27", "open": 1.319, "close": 1.326, "high": 1.329, "low": 1.312, "volume": 70902.0, "amount": 0.0}, {"date": "2026-03-30", "open": 1.324, "close": 1.325, "high": 1.326, "low": 1.312, "volume": 61017.0, "amount": 0.0}, {"date": "2026-03-31", "open": 1.312, "close": 1.304, "high": 1.312, "low": 1.302, "volume": 64693.0, "amount": 0.0}, {"date": "2026-04-01", "open": 1.317, "close": 1.323, "high": 1.327, "low": 1.313, "volume": 76038.0, "amount": 0.0}, {"date": "2026-04-02", "open": 1.33, "close": 1.322, "high": 1.33, "low": 1.317, "volume": 67527.0, "amount": 0.0}, {"date": "2026-04-03", "open": 1.327, "close": 1.32, "high": 1.329, "low": 1.318, "volume": 29287.0, "amount": 0.0}, {"date": "2026-04-07", "open": 1.32, "close": 1.32, "high": 1.33, "low": 1.319, "volume": 29260.0, "amount": 0.0}, {"date": "2026-04-08", "open": 1.325, "close": 1.326, "high": 1.328, "low": 1.318, "volume": 69659.0, "amount": 0.0}, {"date": "2026-04-09", "open": 1.328, "close": 1.327, "high": 1.329, "low": 1.32, "volume": 44971.0, "amount": 0.0}, {"date": "2026-04-10", "open": 1.331, "close": 1.334, "high": 1.34, "low": 1.33, "volume": 58912.0, "amount": 0.0}, {"date": "2026-04-13", "open": 1.33, "close": 1.334, "high": 1.336, "low": 1.326, "volume": 28734.0, "amount": 0.0}, {"date": "2026-04-14", "open": 1.335, "close": 1.338, "high": 1.341, "low": 1.334, "volume": 40296.0, "amount": 0.0}, {"date": "2026-04-15", "open": 1.342, "close": 1.328, "high": 1.343, "low": 1.328, "volume": 43790.0, "amount": 0.0}, {"date": "2026-04-16", "open": 1.329, "close": 1.332, "high": 1.334, "low": 1.329, "volume": 30861.0, "amount": 0.0}, {"date": "2026-04-17", "open": 1.333, "close": 1.325, "high": 1.334, "low": 1.323, "volume": 24549.0, "amount": 0.0}, {"date": "2026-04-20", "open": 1.325, "close": 1.327, "high": 1.331, "low": 1.322, "volume": 23306.0, "amount": 0.0}, {"date": "2026-04-21", "open": 1.327, "close": 1.344, "high": 1.344, "low": 1.327, "volume": 70416.0, "amount": 0.0}, {"date": "2026-04-22", "open": 1.343, "close": 1.331, "high": 1.343, "low": 1.329, "volume": 60566.0, "amount": 0.0}, {"date": "2026-04-23", "open": 1.331, "close": 1.334, "high": 1.337, "low": 1.327, "volume": 54833.0, "amount": 0.0}, {"date": "2026-04-24", "open": 1.333, "close": 1.336, "high": 1.337, "low": 1.328, "volume": 28252.0, "amount": 0.0}, {"date": "2026-04-27", "open": 1.337, "close": 1.331, "high": 1.338, "low": 1.329, "volume": 40107.0, "amount": 0.0}, {"date": "2026-04-28", "open": 1.331, "close": 1.333, "high": 1.334, "low": 1.322, "volume": 52881.0, "amount": 0.0}, {"date": "2026-04-29", "open": 1.341, "close": 1.349, "high": 1.351, "low": 1.336, "volume": 78380.0, "amount": 0.0}, {"date": "2026-04-30", "open": 1.351, "close": 1.335, "high": 1.351, "low": 1.334, "volume": 60468.0, "amount": 0.0}, {"date": "2026-05-06", "open": 1.329, "close": 1.336, "high": 1.337, "low": 1.327, "volume": 50097.0, "amount": 0.0}, {"date": "2026-05-07", "open": 1.336, "close": 1.334, "high": 1.34, "low": 1.331, "volume": 43540.0, "amount": 0.0}, {"date": "2026-05-08", "open": 1.33, "close": 1.331, "high": 1.333, "low": 1.325, "volume": 70726.0, "amount": 0.0}, {"date": "2026-05-11", "open": 1.334, "close": 1.336, "high": 1.336, "low": 1.329, "volume": 53122.0, "amount": 0.0}, {"date": "2026-05-12", "open": 1.338, "close": 1.339, "high": 1.341, "low": 1.335, "volume": 59353.0, "amount": 0.0}, {"date": "2026-05-13", "open": 1.339, "close": 1.335, "high": 1.34, "low": 1.335, "volume": 27446.0, "amount": 0.0}, {"date": "2026-05-14", "open": 1.336, "close": 1.332, "high": 1.341, "low": 1.33, "volume": 48015.0, "amount": 0.0}, {"date": "2026-05-15", "open": 1.333, "close": 1.325, "high": 1.334, "low": 1.323, "volume": 39048.0, "amount": 0.0}, {"date": "2026-05-18", "open": 1.327, "close": 1.32, "high": 1.332, "low": 1.319, "volume": 59030.0, "amount": 0.0}, {"date": "2026-05-19", "open": 1.323, "close": 1.327, "high": 1.331, "low": 1.321, "volume": 32281.0, "amount": 0.0}, {"date": "2026-05-20", "open": 1.327, "close": 1.323, "high": 1.33, "low": 1.32, "volume": 22118.0, "amount": 0.0}, {"date": "2026-05-21", "open": 1.325, "close": 1.317, "high": 1.327, "low": 1.316, "volume": 42177.0, "amount": 0.0}, {"date": "2026-05-22", "open": 1.317, "close": 1.31, "high": 1.319, "low": 1.305, "volume": 35611.0, "amount": 0.0}, {"date": "2026-05-25", "open": 1.31, "close": 1.307, "high": 1.312, "low": 1.306, "volume": 13911.0, "amount": 0.0}, {"date": "2026-05-26", "open": 1.307, "close": 1.308, "high": 1.312, "low": 1.299, "volume": 38799.0, "amount": 0.0}, {"date": "2026-05-27", "open": 1.306, "close": 1.298, "high": 1.306, "low": 1.293, "volume": 64709.0, "amount": 0.0}, {"date": "2026-05-28", "open": 1.298, "close": 1.282, "high": 1.298, "low": 1.276, "volume": 38244.0, "amount": 0.0}, {"date": "2026-05-29", "open": 1.282, "close": 1.294, "high": 1.295, "low": 1.278, "volume": 41340.0, "amount": 0.0}]